NLIMED/NLIMED.py
NLIMED/__init__.py
NLIMED/__main__.py
NLIMED/bs_ner.py
NLIMED/console.py
NLIMED/general.py
NLIMED/query_annotator.py
NLIMED/rdf_graph_index.py
NLIMED/sparql_generator.py
NLIMED/text_feature_index.py
NLIMED/indexes/BM_inv_index
NLIMED/indexes/BM_track.json
NLIMED/indexes/bm-omex_inv_index
NLIMED/indexes/bm-omex_inv_index_onto
NLIMED/indexes/bm-omex_object.json
NLIMED/indexes/bm-omex_pred_inv_index
NLIMED/indexes/bm-omex_pred_inv_index_onto
NLIMED/indexes/bm-omex_predicate.json
NLIMED/indexes/bm-omex_rdfPaths
NLIMED/indexes/bm-omex_track.json
NLIMED/indexes/bm_object.json
NLIMED/indexes/bm_rdfPaths
NLIMED/indexes/pmr_idx_id_object
NLIMED/indexes/pmr_idx_id_pred
NLIMED/indexes/pmr_idx_id_subject
NLIMED/indexes/pmr_idx_id_track
NLIMED/indexes/pmr_idx_obj_sbj
NLIMED/indexes/pmr_idx_object_id
NLIMED/indexes/pmr_idx_pref_ns
NLIMED/indexes/pmr_idx_sbjobj_tracks
NLIMED/indexes/pmr_idx_subject_id
NLIMED/indexes/pmr_inv_index
NLIMED/indexes/pmr_inv_index_onto
NLIMED/indexes/pmr_pred_inv_index
NLIMED/indexes/pmr_pred_inv_index_onto
NLIMED-0.0.2.dist-info/METADATA
NLIMED-0.0.2.dist-info/WHEEL
NLIMED-0.0.2.dist-info/entry_points.txt
NLIMED-0.0.2.dist-info/top_level.txt
NLIMED-0.0.2.dist-info/RECORD
