Metadata-Version: 2.1
Name: NLIMED
Version: 0.0.2
Summary: Natural Language Interface for Model Entity Discovery (NLIMED) is an interface to search model entities in the biosimulation models in repositories. 
Home-page: https://github.com/napakalas/NLIMED
Author: Yuda Munarko
Author-email: yuda.munarko@gmail.com
License: UNKNOWN
Platform: UNKNOWN
Classifier: Programming Language :: Python :: 3
Classifier: License :: OSI Approved :: GNU General Public License (GPL)
Classifier: Operating System :: OS Independent
Requires-Dist: nltk
Requires-Dist: SPARQLWrapper
Requires-Dist: pandas
Requires-Dist: stanza
Requires-Dist: benepar
